[
  { "book": "Matthew", "chapter": 11, "verse": 28, "emotionId": "stressed", "emotionTags": ["stressed"], "tags": ["rest", "burden"], "tier": "free", "weight": 10 },
  { "book": "Philippians", "chapter": 4, "verse": 6, "emotionId": "stressed", "emotionTags": ["stressed"], "tags": ["peace", "anxiety"], "tier": "free", "weight": 10 },
  { "book": "Philippians", "chapter": 4, "verse": 7, "emotionId": "stressed", "emotionTags": ["stressed"], "tags": ["peace", "mind"], "tier": "free", "weight": 9 },
  { "book": "1 Peter", "chapter": 5, "verse": 7, "emotionId": "stressed", "emotionTags": ["stressed"], "tags": ["worry", "care"], "tier": "free", "weight": 10 },
  { "book": "Isaiah", "chapter": 26, "verse": 3, "emotionId": "stressed", "emotionTags": ["stressed"], "tags": ["peace", "trust"], "tier": "free", "weight": 9 },
  { "book": "Psalm", "chapter": 46, "verse": 1, "emotionId": "stressed", "emotionTags": ["stressed"], "tags": ["refuge", "strength"], "tier": "free", "weight": 9 },
  { "book": "Psalm", "chapter": 46, "verse": 10, "emotionId": "stressed", "emotionTags": ["stressed"], "tags": ["stillness", "trust"], "tier": "free", "weight": 9 },
  { "book": "John", "chapter": 14, "verse": 27, "emotionId": "stressed", "emotionTags": ["stressed"], "tags": ["peace", "fear"], "tier": "free", "weight": 10 },
  { "book": "Romans", "chapter": 8, "verse": 28, "emotionId": "stressed", "emotionTags": ["stressed"], "tags": ["purpose", "trust"], "tier": "free", "weight": 9 },
  { "book": "2 Timothy", "chapter": 1, "verse": 7, "emotionId": "stressed", "emotionTags": ["stressed"], "tags": ["courage", "fear"], "tier": "free", "weight": 9 },
  { "book": "Joshua", "chapter": 1, "verse": 9, "emotionId": "stressed", "emotionTags": ["stressed"], "tags": ["courage", "presence"], "tier": "free", "weight": 9 },
  { "book": "Isaiah", "chapter": 41, "verse": 10, "emotionId": "stressed", "emotionTags": ["stressed"], "tags": ["strength", "fear"], "tier": "free", "weight": 10 },
  { "book": "Psalm", "chapter": 55, "verse": 22, "emotionId": "stressed", "emotionTags": ["stressed"], "tags": ["burden", "care"], "tier": "free", "weight": 8 },
  { "book": "Matthew", "chapter": 6, "verse": 34, "emotionId": "stressed", "emotionTags": ["stressed"], "tags": ["anxiety", "present"], "tier": "free", "weight": 8 },
  { "book": "Luke", "chapter": 12, "verse": 25, "emotionId": "stressed", "emotionTags": ["stressed"], "tags": ["worry", "futility"], "tier": "free", "weight": 8 },
  { "book": "Proverbs", "chapter": 3, "verse": 5, "emotionId": "stressed", "emotionTags": ["stressed"], "tags": ["trust", "understanding"], "tier": "free", "weight": 9 },
  { "book": "Proverbs", "chapter": 3, "verse": 6, "emotionId": "stressed", "emotionTags": ["stressed"], "tags": ["direction", "trust"], "tier": "free", "weight": 9 },
  { "book": "Psalm", "chapter": 94, "verse": 19, "emotionId": "stressed", "emotionTags": ["stressed"], "tags": ["anxiety", "comfort"], "tier": "free", "weight": 8 },
  { "book": "Romans", "chapter": 15, "verse": 13, "emotionId": "stressed", "emotionTags": ["stressed"], "tags": ["hope", "peace"], "tier": "free", "weight": 9 },
  { "book": "2 Thessalonians", "chapter": 3, "verse": 16, "emotionId": "stressed", "emotionTags": ["stressed"], "tags": ["peace", "presence"], "tier": "free", "weight": 8 },
  { "book": "Numbers", "chapter": 6, "verse": 26, "emotionId": "stressed", "emotionTags": ["stressed"], "tags": ["peace", "grace"], "tier": "free", "weight": 8 },
  { "book": "Psalm", "chapter": 29, "verse": 11, "emotionId": "stressed", "emotionTags": ["stressed"], "tags": ["strength", "peace"], "tier": "free", "weight": 8 },
  { "book": "Isaiah", "chapter": 30, "verse": 15, "emotionId": "stressed", "emotionTags": ["stressed"], "tags": ["rest", "quietness"], "tier": "free", "weight": 8 },
  { "book": "Hebrews", "chapter": 4, "verse": 16, "emotionId": "stressed", "emotionTags": ["stressed"], "tags": ["grace", "help"], "tier": "free", "weight": 9 },
  { "book": "Exodus", "chapter": 14, "verse": 14, "emotionId": "stressed", "emotionTags": ["stressed"], "tags": ["stillness", "battle"], "tier": "free", "weight": 8 },
  { "book": "Matthew", "chapter": 6, "verse": 27, "emotionId": "stressed", "emotionTags": ["stressed"], "tags": ["worry", "futility"], "tier": "premium", "weight": 8 },
  { "book": "Luke", "chapter": 21, "verse": 34, "emotionId": "stressed", "emotionTags": ["stressed"], "tags": ["anxiety", "watchfulness"], "tier": "premium", "weight": 8 },
  { "book": "Colossians", "chapter": 3, "verse": 15, "emotionId": "stressed", "emotionTags": ["stressed"], "tags": ["peace", "gratitude"], "tier": "premium", "weight": 9 },
  { "book": "Psalm", "chapter": 37, "verse": 5, "emotionId": "stressed", "emotionTags": ["stressed"], "tags": ["trust", "delight"], "tier": "premium", "weight": 9 },
  { "book": "Psalm", "chapter": 37, "verse": 7, "emotionId": "stressed", "emotionTags": ["stressed"], "tags": ["patience", "stillness"], "tier": "premium", "weight": 8 },
  { "book": "Isaiah", "chapter": 43, "verse": 2, "emotionId": "stressed", "emotionTags": ["stressed"], "tags": ["presence", "protection"], "tier": "premium", "weight": 9 },
  { "book": "Nahum", "chapter": 1, "verse": 7, "emotionId": "stressed", "emotionTags": ["stressed"], "tags": ["refuge", "care"], "tier": "premium", "weight": 8 },
  { "book": "Zephaniah", "chapter": 3, "verse": 17, "emotionId": "stressed", "emotionTags": ["stressed"], "tags": ["delight", "love"], "tier": "premium", "weight": 9 },
  { "book": "Psalm", "chapter": 91, "verse": 1, "emotionId": "stressed", "emotionTags": ["stressed"], "tags": ["refuge", "shelter"], "tier": "premium", "weight": 9 },
  { "book": "Psalm", "chapter": 91, "verse": 2, "emotionId": "stressed", "emotionTags": ["stressed"], "tags": ["refuge", "trust"], "tier": "premium", "weight": 8 },
  { "book": "Deuteronomy", "chapter": 31, "verse": 6, "emotionId": "stressed", "emotionTags": ["stressed"], "tags": ["courage", "presence"], "tier": "premium", "weight": 9 },
  { "book": "1 Chronicles", "chapter": 28, "verse": 20, "emotionId": "stressed", "emotionTags": ["stressed"], "tags": ["courage", "fear"], "tier": "premium", "weight": 8 },
  { "book": "Psalm", "chapter": 27, "verse": 1, "emotionId": "stressed", "emotionTags": ["stressed"], "tags": ["strength", "fear"], "tier": "premium", "weight": 9 },
  { "book": "Psalm", "chapter": 27, "verse": 14, "emotionId": "stressed", "emotionTags": ["stressed"], "tags": ["patience", "strength"], "tier": "premium", "weight": 8 },
  { "book": "Psalm", "chapter": 62, "verse": 1, "emotionId": "stressed", "emotionTags": ["stressed"], "tags": ["rest", "trust"], "tier": "premium", "weight": 8 },
  { "book": "Lamentations", "chapter": 3, "verse": 26, "emotionId": "stressed", "emotionTags": ["stressed"], "tags": ["patience", "hope"], "tier": "premium", "weight": 8 },
  { "book": "Habakkuk", "chapter": 3, "verse": 19, "emotionId": "stressed", "emotionTags": ["stressed"], "tags": ["strength", "heights"], "tier": "premium", "weight": 8 },
  { "book": "James", "chapter": 4, "verse": 8, "emotionId": "stressed", "emotionTags": ["stressed"], "tags": ["nearness", "drawing"], "tier": "premium", "weight": 8 },
  { "book": "Psalm", "chapter": 16, "verse": 8, "emotionId": "stressed", "emotionTags": ["stressed"], "tags": ["steadiness", "presence"], "tier": "premium", "weight": 8 },
  { "book": "Isaiah", "chapter": 26, "verse": 4, "emotionId": "stressed", "emotionTags": ["stressed"], "tags": ["trust", "strength"], "tier": "premium", "weight": 8 },
  { "book": "Romans", "chapter": 5, "verse": 1, "emotionId": "stressed", "emotionTags": ["stressed"], "tags": ["peace", "faith"], "tier": "premium", "weight": 8 },
  { "book": "Galatians", "chapter": 6, "verse": 9, "emotionId": "stressed", "emotionTags": ["stressed"], "tags": ["perseverance", "harvest"], "tier": "premium", "weight": 8 },
  { "book": "Isaiah", "chapter": 40, "verse": 29, "emotionId": "stressed", "emotionTags": ["stressed"], "tags": ["strength", "weary"], "tier": "premium", "weight": 9 },
  { "book": "Isaiah", "chapter": 40, "verse": 31, "emotionId": "stressed", "emotionTags": ["stressed"], "tags": ["strength", "renewal"], "tier": "premium", "weight": 10 },
  { "book": "2 Corinthians", "chapter": 1, "verse": 3, "emotionId": "stressed", "emotionTags": ["stressed"], "tags": ["comfort", "mercy"], "tier": "premium", "weight": 9 },

  { "book": "Isaiah", "chapter": 40, "verse": 31, "emotionId": "tired", "emotionTags": ["tired"], "tags": ["renewal", "strength"], "tier": "free", "weight": 10 },
  { "book": "Matthew", "chapter": 11, "verse": 28, "emotionId": "tired", "emotionTags": ["tired"], "tags": ["rest", "weary"], "tier": "free", "weight": 10 },
  { "book": "Matthew", "chapter": 11, "verse": 29, "emotionId": "tired", "emotionTags": ["tired"], "tags": ["rest", "soul"], "tier": "free", "weight": 10 },
  { "book": "Psalm", "chapter": 23, "verse": 1, "emotionId": "tired", "emotionTags": ["tired"], "tags": ["rest", "shepherd"], "tier": "free", "weight": 9 },
  { "book": "Psalm", "chapter": 23, "verse": 2, "emotionId": "tired", "emotionTags": ["tired"], "tags": ["rest", "restoration"], "tier": "free", "weight": 9 },
  { "book": "Psalm", "chapter": 23, "verse": 3, "emotionId": "tired", "emotionTags": ["tired"], "tags": ["restoration", "paths"], "tier": "free", "weight": 9 },
  { "book": "Psalm", "chapter": 121, "verse": 1, "emotionId": "tired", "emotionTags": ["tired"], "tags": ["help", "hills"], "tier": "free", "weight": 9 },
  { "book": "Psalm", "chapter": 121, "verse": 2, "emotionId": "tired", "emotionTags": ["tired"], "tags": ["help", "maker"], "tier": "free", "weight": 9 },
  { "book": "Psalm", "chapter": 121, "verse": 3, "emotionId": "tired", "emotionTags": ["tired"], "tags": ["watchfulness", "slumber"], "tier": "free", "weight": 8 },
  { "book": "Galatians", "chapter": 6, "verse": 9, "emotionId": "tired", "emotionTags": ["tired"], "tags": ["perseverance", "harvest"], "tier": "free", "weight": 9 },
  { "book": "2 Corinthians", "chapter": 4, "verse": 16, "emotionId": "tired", "emotionTags": ["tired"], "tags": ["renewal", "inner"], "tier": "free", "weight": 9 },
  { "book": "2 Corinthians", "chapter": 4, "verse": 17, "emotionId": "tired", "emotionTags": ["tired"], "tags": ["glory", "momentary"], "tier": "free", "weight": 9 },
  { "book": "Isaiah", "chapter": 40, "verse": 28, "emotionId": "tired", "emotionTags": ["tired"], "tags": ["everlasting", "strength"], "tier": "free", "weight": 9 },
  { "book": "Isaiah", "chapter": 40, "verse": 29, "emotionId": "tired", "emotionTags": ["tired"], "tags": ["strength", "weary"], "tier": "free", "weight": 9 },
  { "book": "Psalm", "chapter": 4, "verse": 8, "emotionId": "tired", "emotionTags": ["tired"], "tags": ["sleep", "safety"], "tier": "free", "weight": 8 },
  { "book": "Proverbs", "chapter": 3, "verse": 24, "emotionId": "tired", "emotionTags": ["tired"], "tags": ["sleep", "fear"], "tier": "free", "weight": 8 },
  { "book": "Psalm", "chapter": 127, "verse": 2, "emotionId": "tired", "emotionTags": ["tired"], "tags": ["sleep", "beloved"], "tier": "free", "weight": 8 },
  { "book": "Hebrews", "chapter": 12, "verse": 3, "emotionId": "tired", "emotionTags": ["tired"], "tags": ["perseverance", "weariness"], "tier": "free", "weight": 8 },
  { "book": "Romans", "chapter": 8, "verse": 26, "emotionId": "tired", "emotionTags": ["tired"], "tags": ["weakness", "intercession"], "tier": "free", "weight": 9 },
  { "book": "Psalm", "chapter": 73, "verse": 26, "emotionId": "tired", "emotionTags": ["tired"], "tags": ["strength", "portion"], "tier": "free", "weight": 9 },
  { "book": "Mark", "chapter": 6, "verse": 31, "emotionId": "tired", "emotionTags": ["tired"], "tags": ["rest", "quiet"], "tier": "free", "weight": 8 },
  { "book": "Exodus", "chapter": 33, "verse": 14, "emotionId": "tired", "emotionTags": ["tired"], "tags": ["rest", "presence"], "tier": "free", "weight": 9 },
  { "book": "Lamentations", "chapter": 3, "verse": 22, "emotionId": "tired", "emotionTags": ["tired"], "tags": ["mercy", "renewal"], "tier": "free", "weight": 9 },
  { "book": "Lamentations", "chapter": 3, "verse": 23, "emotionId": "tired", "emotionTags": ["tired"], "tags": ["mercies", "morning"], "tier": "free", "weight": 9 },
  { "book": "Revelation", "chapter": 21, "verse": 4, "emotionId": "tired", "emotionTags": ["tired"], "tags": ["tears", "comfort"], "tier": "free", "weight": 9 },
  { "book": "Zephaniah", "chapter": 3, "verse": 17, "emotionId": "tired", "emotionTags": ["tired"], "tags": ["delight", "quiet"], "tier": "premium", "weight": 9 },
  { "book": "Psalm", "chapter": 46, "verse": 10, "emotionId": "tired", "emotionTags": ["tired"], "tags": ["stillness", "rest"], "tier": "premium", "weight": 9 },
  { "book": "Isaiah", "chapter": 30, "verse": 15, "emotionId": "tired", "emotionTags": ["tired"], "tags": ["rest", "quietness"], "tier": "premium", "weight": 8 },
  { "book": "Job", "chapter": 34, "verse": 4, "emotionId": "tired", "emotionTags": ["tired"], "tags": ["understanding", "good"], "tier": "premium", "weight": 8 },
  { "book": "Jeremiah", "chapter": 31, "verse": 25, "emotionId": "tired", "emotionTags": ["tired"], "tags": ["refreshment", "weary"], "tier": "premium", "weight": 9 },
  { "book": "Psalm", "chapter": 116, "verse": 7, "emotionId": "tired", "emotionTags": ["tired"], "tags": ["rest", "soul"], "tier": "premium", "weight": 8 },
  { "book": "Psalm", "chapter": 62, "verse": 1, "emotionId": "tired", "emotionTags": ["tired"], "tags": ["rest", "soul"], "tier": "premium", "weight": 8 },
  { "book": "Psalm", "chapter": 62, "verse": 5, "emotionId": "tired", "emotionTags": ["tired"], "tags": ["hope", "rest"], "tier": "premium", "weight": 8 },
  { "book": "Psalm", "chapter": 37, "verse": 7, "emotionId": "tired", "emotionTags": ["tired"], "tags": ["patience", "stillness"], "tier": "premium", "weight": 8 },
  { "book": "Hebrews", "chapter": 4, "verse": 9, "emotionId": "tired", "emotionTags": ["tired"], "tags": ["sabbath", "rest"], "tier": "premium", "weight": 8 },
  { "book": "Hebrews", "chapter": 4, "verse": 10, "emotionId": "tired", "emotionTags": ["tired"], "tags": ["rest", "labor"], "tier": "premium", "weight": 8 },
  { "book": "John", "chapter": 4, "verse": 14, "emotionId": "tired", "emotionTags": ["tired"], "tags": ["water", "thirst"], "tier": "premium", "weight": 8 },
  { "book": "Psalm", "chapter": 84, "verse": 11, "emotionId": "tired", "emotionTags": ["tired"], "tags": ["sun", "shield"], "tier": "premium", "weight": 8 },
  { "book": "Isaiah", "chapter": 58, "verse": 11, "emotionId": "tired", "emotionTags": ["tired"], "tags": ["guidance", "satisfaction"], "tier": "premium", "weight": 8 },
  { "book": "Psalm", "chapter": 145, "verse": 14, "emotionId": "tired", "emotionTags": ["tired"], "tags": ["lifting", "bowed"], "tier": "premium", "weight": 8 },
  { "book": "Philippians", "chapter": 4, "verse": 13, "emotionId": "tired", "emotionTags": ["tired"], "tags": ["strength", "christ"], "tier": "premium", "weight": 10 },
  { "book": "Romans", "chapter": 8, "verse": 11, "emotionId": "tired", "emotionTags": ["tired"], "tags": ["life", "spirit"], "tier": "premium", "weight": 9 },
  { "book": "Ephesians", "chapter": 3, "verse": 16, "emotionId": "tired", "emotionTags": ["tired"], "tags": ["strength", "inner"], "tier": "premium", "weight": 9 },
  { "book": "1 Corinthians", "chapter": 15, "verse": 58, "emotionId": "tired", "emotionTags": ["tired"], "tags": ["labor", "purpose"], "tier": "premium", "weight": 8 },
  { "book": "Numbers", "chapter": 11, "verse": 23, "emotionId": "tired", "emotionTags": ["tired"], "tags": ["power", "limit"], "tier": "premium", "weight": 8 },
  { "book": "Psalm", "chapter": 31, "verse": 24, "emotionId": "tired", "emotionTags": ["tired"], "tags": ["courage", "hope"], "tier": "premium", "weight": 8 },
  { "book": "Acts", "chapter": 3, "verse": 19, "emotionId": "tired", "emotionTags": ["tired"], "tags": ["refreshment", "times"], "tier": "premium", "weight": 8 },
  { "book": "Isaiah", "chapter": 35, "verse": 3, "emotionId": "tired", "emotionTags": ["tired"], "tags": ["strengthening", "feeble"], "tier": "premium", "weight": 8 },
  { "book": "Isaiah", "chapter": 35, "verse": 4, "emotionId": "tired", "emotionTags": ["tired"], "tags": ["courage", "fear"], "tier": "premium", "weight": 8 },
  { "book": "2 Corinthians", "chapter": 12, "verse": 9, "emotionId": "tired", "emotionTags": ["tired"], "tags": ["grace", "weakness"], "tier": "premium", "weight": 9 },

  { "book": "Psalm", "chapter": 34, "verse": 18, "emotionId": "sad", "emotionTags": ["sad"], "tags": ["grief", "presence"], "tier": "free", "weight": 10 },
  { "book": "Psalm", "chapter": 147, "verse": 3, "emotionId": "sad", "emotionTags": ["sad"], "tags": ["healing", "brokenhearted"], "tier": "free", "weight": 10 },
  { "book": "Matthew", "chapter": 5, "verse": 4, "emotionId": "sad", "emotionTags": ["sad"], "tags": ["mourning", "comfort"], "tier": "free", "weight": 10 },
  { "book": "Revelation", "chapter": 21, "verse": 4, "emotionId": "sad", "emotionTags": ["sad"], "tags": ["tears", "comfort"], "tier": "free", "weight": 10 },
  { "book": "John", "chapter": 11, "verse": 35, "emotionId": "sad", "emotionTags": ["sad"], "tags": ["grief", "tears"], "tier": "free", "weight": 9 },
  { "book": "Psalm", "chapter": 30, "verse": 5, "emotionId": "sad", "emotionTags": ["sad"], "tags": ["weeping", "joy"], "tier": "free", "weight": 9 },
  { "book": "Psalm", "chapter": 56, "verse": 8, "emotionId": "sad", "emotionTags": ["sad"], "tags": ["tears", "seen"], "tier": "free", "weight": 9 },
  { "book": "Isaiah", "chapter": 61, "verse": 3, "emotionId": "sad", "emotionTags": ["sad"], "tags": ["beauty", "mourning"], "tier": "free", "weight": 9 },
  { "book": "2 Corinthians", "chapter": 1, "verse": 3, "emotionId": "sad", "emotionTags": ["sad"], "tags": ["comfort", "affliction"], "tier": "free", "weight": 9 },
  { "book": "2 Corinthians", "chapter": 1, "verse": 4, "emotionId": "sad", "emotionTags": ["sad"], "tags": ["comfort", "compassion"], "tier": "free", "weight": 9 },
  { "book": "Psalm", "chapter": 9, "verse": 9, "emotionId": "sad", "emotionTags": ["sad"], "tags": ["refuge", "oppressed"], "tier": "free", "weight": 8 },
  { "book": "Psalm", "chapter": 46, "verse": 1, "emotionId": "sad", "emotionTags": ["sad"], "tags": ["refuge", "strength"], "tier": "free", "weight": 9 },
  { "book": "Isaiah", "chapter": 53, "verse": 3, "emotionId": "sad", "emotionTags": ["sad"], "tags": ["sorrow", "known"], "tier": "free", "weight": 9 },
  { "book": "Romans", "chapter": 8, "verse": 26, "emotionId": "sad", "emotionTags": ["sad"], "tags": ["weakness", "intercession"], "tier": "free", "weight": 9 },
  { "book": "Romans", "chapter": 8, "verse": 28, "emotionId": "sad", "emotionTags": ["sad"], "tags": ["purpose", "good"], "tier": "free", "weight": 8 },
  { "book": "Psalm", "chapter": 22, "verse": 24, "emotionId": "sad", "emotionTags": ["sad"], "tags": ["affliction", "heard"], "tier": "free", "weight": 8 },
  { "book": "Psalm", "chapter": 40, "verse": 1, "emotionId": "sad", "emotionTags": ["sad"], "tags": ["waiting", "heard"], "tier": "free", "weight": 8 },
  { "book": "Psalm", "chapter": 40, "verse": 2, "emotionId": "sad", "emotionTags": ["sad"], "tags": ["pit", "lifted"], "tier": "free", "weight": 9 },
  { "book": "Isaiah", "chapter": 43, "verse": 1, "emotionId": "sad", "emotionTags": ["sad"], "tags": ["name", "called"], "tier": "free", "weight": 9 },
  { "book": "Isaiah", "chapter": 43, "verse": 2, "emotionId": "sad", "emotionTags": ["sad"], "tags": ["waters", "fire"], "tier": "free", "weight": 9 },
  { "book": "Lamentations", "chapter": 3, "verse": 22, "emotionId": "sad", "emotionTags": ["sad"], "tags": ["mercy", "love"], "tier": "free", "weight": 9 },
  { "book": "Lamentations", "chapter": 3, "verse": 23, "emotionId": "sad", "emotionTags": ["sad"], "tags": ["morning", "mercies"], "tier": "free", "weight": 9 },
  { "book": "Psalm", "chapter": 71, "verse": 20, "emotionId": "sad", "emotionTags": ["sad"], "tags": ["restore", "depths"], "tier": "free", "weight": 8 },
  { "book": "Joel", "chapter": 2, "verse": 25, "emotionId": "sad", "emotionTags": ["sad"], "tags": ["restore", "years"], "tier": "free", "weight": 9 },
  { "book": "Psalm", "chapter": 31, "verse": 7, "emotionId": "sad", "emotionTags": ["sad"], "tags": ["known", "mercy"], "tier": "free", "weight": 8 },
  { "book": "Jeremiah", "chapter": 29, "verse": 11, "emotionId": "sad", "emotionTags": ["sad"], "tags": ["hope", "future"], "tier": "premium", "weight": 10 },
  { "book": "Isaiah", "chapter": 40, "verse": 31, "emotionId": "sad", "emotionTags": ["sad"], "tags": ["renewal", "strength"], "tier": "premium", "weight": 9 },
  { "book": "Psalm", "chapter": 34, "verse": 4, "emotionId": "sad", "emotionTags": ["sad"], "tags": ["fear", "deliverance"], "tier": "premium", "weight": 8 },
  { "book": "Psalm", "chapter": 34, "verse": 6, "emotionId": "sad", "emotionTags": ["sad"], "tags": ["poor", "answered"], "tier": "premium", "weight": 8 },
  { "book": "Romans", "chapter": 15, "verse": 13, "emotionId": "sad", "emotionTags": ["sad"], "tags": ["hope", "peace"], "tier": "premium", "weight": 9 },
  { "book": "Psalm", "chapter": 73, "verse": 26, "emotionId": "sad", "emotionTags": ["sad"], "tags": ["strength", "portion"], "tier": "premium", "weight": 9 },
  { "book": "Hebrews", "chapter": 13, "verse": 5, "emotionId": "sad", "emotionTags": ["sad"], "tags": ["never", "forsaken"], "tier": "premium", "weight": 9 },
  { "book": "Deuteronomy", "chapter": 31, "verse": 8, "emotionId": "sad", "emotionTags": ["sad"], "tags": ["presence", "forsaken"], "tier": "premium", "weight": 9 },
  { "book": "Psalm", "chapter": 10, "verse": 14, "emotionId": "sad", "emotionTags": ["sad"], "tags": ["seen", "orphan"], "tier": "premium", "weight": 8 },
  { "book": "Psalm", "chapter": 139, "verse": 16, "emotionId": "sad", "emotionTags": ["sad"], "tags": ["days", "written"], "tier": "premium", "weight": 8 },
  { "book": "Psalm", "chapter": 139, "verse": 17, "emotionId": "sad", "emotionTags": ["sad"], "tags": ["thoughts", "precious"], "tier": "premium", "weight": 8 },
  { "book": "Job", "chapter": 19, "verse": 25, "emotionId": "sad", "emotionTags": ["sad"], "tags": ["redeemer", "lives"], "tier": "premium", "weight": 9 },
  { "book": "1 Peter", "chapter": 5, "verse": 7, "emotionId": "sad", "emotionTags": ["sad"], "tags": ["care", "casting"], "tier": "premium", "weight": 9 },
  { "book": "James", "chapter": 4, "verse": 8, "emotionId": "sad", "emotionTags": ["sad"], "tags": ["nearness", "drawing"], "tier": "premium", "weight": 8 },
  { "book": "Psalm", "chapter": 91, "verse": 4, "emotionId": "sad", "emotionTags": ["sad"], "tags": ["refuge", "wings"], "tier": "premium", "weight": 9 },
  { "book": "Hosea", "chapter": 6, "verse": 1, "emotionId": "sad", "emotionTags": ["sad"], "tags": ["healing", "return"], "tier": "premium", "weight": 8 },
  { "book": "Psalm", "chapter": 126, "verse": 5, "emotionId": "sad", "emotionTags": ["sad"], "tags": ["tears", "harvest"], "tier": "premium", "weight": 8 },
  { "book": "Isaiah", "chapter": 41, "verse": 10, "emotionId": "sad", "emotionTags": ["sad"], "tags": ["strength", "fear"], "tier": "premium", "weight": 9 },
  { "book": "Romans", "chapter": 8, "verse": 38, "emotionId": "sad", "emotionTags": ["sad"], "tags": ["love", "separation"], "tier": "premium", "weight": 9 },
  { "book": "Romans", "chapter": 8, "verse": 39, "emotionId": "sad", "emotionTags": ["sad"], "tags": ["love", "separation"], "tier": "premium", "weight": 9 },
  { "book": "Psalm", "chapter": 116, "verse": 15, "emotionId": "sad", "emotionTags": ["sad"], "tags": ["death", "precious"], "tier": "premium", "weight": 8 },
  { "book": "Ecclesiastes", "chapter": 3, "verse": 4, "emotionId": "sad", "emotionTags": ["sad"], "tags": ["mourning", "time"], "tier": "premium", "weight": 8 },
  { "book": "Psalm", "chapter": 69, "verse": 33, "emotionId": "sad", "emotionTags": ["sad"], "tags": ["poor", "heard"], "tier": "premium", "weight": 8 },
  { "book": "Isaiah", "chapter": 66, "verse": 13, "emotionId": "sad", "emotionTags": ["sad"], "tags": ["comfort", "mother"], "tier": "premium", "weight": 8 },
  { "book": "Zephaniah", "chapter": 3, "verse": 17, "emotionId": "sad", "emotionTags": ["sad"], "tags": ["joy", "singing"], "tier": "premium", "weight": 9 },

  { "book": "Psalm", "chapter": 139, "verse": 14, "emotionId": "neutral", "emotionTags": ["neutral"], "tags": ["fearfully", "made"], "tier": "free", "weight": 10 },
  { "book": "Jeremiah", "chapter": 29, "verse": 11, "emotionId": "neutral", "emotionTags": ["neutral"], "tags": ["hope", "purpose"], "tier": "free", "weight": 10 },
  { "book": "Proverbs", "chapter": 3, "verse": 5, "emotionId": "neutral", "emotionTags": ["neutral"], "tags": ["trust", "understanding"], "tier": "free", "weight": 9 },
  { "book": "Proverbs", "chapter": 3, "verse": 6, "emotionId": "neutral", "emotionTags": ["neutral"], "tags": ["direction", "paths"], "tier": "free", "weight": 9 },
  { "book": "Philippians", "chapter": 4, "verse": 11, "emotionId": "neutral", "emotionTags": ["neutral"], "tags": ["contentment", "learned"], "tier": "free", "weight": 9 },
  { "book": "Philippians", "chapter": 4, "verse": 12, "emotionId": "neutral", "emotionTags": ["neutral"], "tags": ["contentment", "secret"], "tier": "free", "weight": 9 },
  { "book": "Romans", "chapter": 12, "verse": 2, "emotionId": "neutral", "emotionTags": ["neutral"], "tags": ["transformed", "renewal"], "tier": "free", "weight": 9 },
  { "book": "2 Corinthians", "chapter": 5, "verse": 17, "emotionId": "neutral", "emotionTags": ["neutral"], "tags": ["new", "creation"], "tier": "free", "weight": 9 },
  { "book": "Psalm", "chapter": 16, "verse": 11, "emotionId": "neutral", "emotionTags": ["neutral"], "tags": ["joy", "presence"], "tier": "free", "weight": 9 },
  { "book": "Colossians", "chapter": 3, "verse": 2, "emotionId": "neutral", "emotionTags": ["neutral"], "tags": ["mind", "above"], "tier": "free", "weight": 8 },
  { "book": "Romans", "chapter": 8, "verse": 28, "emotionId": "neutral", "emotionTags": ["neutral"], "tags": ["purpose", "good"], "tier": "free", "weight": 9 },
  { "book": "Psalm", "chapter": 46, "verse": 10, "emotionId": "neutral", "emotionTags": ["neutral"], "tags": ["stillness", "knowing"], "tier": "free", "weight": 8 },
  { "book": "Isaiah", "chapter": 55, "verse": 8, "emotionId": "neutral", "emotionTags": ["neutral"], "tags": ["thoughts", "ways"], "tier": "free", "weight": 8 },
  { "book": "Isaiah", "chapter": 55, "verse": 9, "emotionId": "neutral", "emotionTags": ["neutral"], "tags": ["higher", "ways"], "tier": "free", "weight": 8 },
  { "book": "Proverbs", "chapter": 16, "verse": 9, "emotionId": "neutral", "emotionTags": ["neutral"], "tags": ["steps", "direction"], "tier": "free", "weight": 8 },
  { "book": "Psalm", "chapter": 37, "verse": 23, "emotionId": "neutral", "emotionTags": ["neutral"], "tags": ["steps", "ordered"], "tier": "free", "weight": 8 },
  { "book": "Ecclesiastes", "chapter": 3, "verse": 1, "emotionId": "neutral", "emotionTags": ["neutral"], "tags": ["season", "time"], "tier": "free", "weight": 8 },
  { "book": "Ephesians", "chapter": 2, "verse": 10, "emotionId": "neutral", "emotionTags": ["neutral"], "tags": ["workmanship", "purpose"], "tier": "free", "weight": 9 },
  { "book": "Psalm", "chapter": 119, "verse": 105, "emotionId": "neutral", "emotionTags": ["neutral"], "tags": ["lamp", "word"], "tier": "free", "weight": 9 },
  { "book": "John", "chapter": 10, "verse": 10, "emotionId": "neutral", "emotionTags": ["neutral"], "tags": ["life", "abundant"], "tier": "free", "weight": 9 },
  { "book": "Micah", "chapter": 6, "verse": 8, "emotionId": "neutral", "emotionTags": ["neutral"], "tags": ["justice", "humility"], "tier": "free", "weight": 8 },
  { "book": "Romans", "chapter": 5, "verse": 3, "emotionId": "neutral", "emotionTags": ["neutral"], "tags": ["suffering", "perseverance"], "tier": "free", "weight": 8 },
  { "book": "Romans", "chapter": 5, "verse": 4, "emotionId": "neutral", "emotionTags": ["neutral"], "tags": ["character", "hope"], "tier": "free", "weight": 8 },
  { "book": "James", "chapter": 1, "verse": 5, "emotionId": "neutral", "emotionTags": ["neutral"], "tags": ["wisdom", "ask"], "tier": "free", "weight": 9 },
  { "book": "Hebrews", "chapter": 11, "verse": 1, "emotionId": "neutral", "emotionTags": ["neutral"], "tags": ["faith", "hope"], "tier": "free", "weight": 9 },
  { "book": "Matthew", "chapter": 6, "verse": 33, "emotionId": "neutral", "emotionTags": ["neutral"], "tags": ["seeking", "kingdom"], "tier": "premium", "weight": 9 },
  { "book": "Psalm", "chapter": 37, "verse": 4, "emotionId": "neutral", "emotionTags": ["neutral"], "tags": ["delight", "desires"], "tier": "premium", "weight": 9 },
  { "book": "Psalm", "chapter": 37, "verse": 5, "emotionId": "neutral", "emotionTags": ["neutral"], "tags": ["commit", "trust"], "tier": "premium", "weight": 9 },
  { "book": "1 Corinthians", "chapter": 10, "verse": 31, "emotionId": "neutral", "emotionTags": ["neutral"], "tags": ["glory", "purpose"], "tier": "premium", "weight": 8 },
  { "book": "Colossians", "chapter": 3, "verse": 17, "emotionId": "neutral", "emotionTags": ["neutral"], "tags": ["thanksgiving", "name"], "tier": "premium", "weight": 8 },
  { "book": "Philippians", "chapter": 1, "verse": 6, "emotionId": "neutral", "emotionTags": ["neutral"], "tags": ["completion", "work"], "tier": "premium", "weight": 9 },
  { "book": "Isaiah", "chapter": 40, "verse": 31, "emotionId": "neutral", "emotionTags": ["neutral"], "tags": ["renewing", "wait"], "tier": "premium", "weight": 9 },
  { "book": "Lamentations", "chapter": 3, "verse": 25, "emotionId": "neutral", "emotionTags": ["neutral"], "tags": ["waiting", "seeking"], "tier": "premium", "weight": 8 },
  { "book": "Psalm", "chapter": 23, "verse": 6, "emotionId": "neutral", "emotionTags": ["neutral"], "tags": ["goodness", "dwelling"], "tier": "premium", "weight": 9 },
  { "book": "Galatians", "chapter": 5, "verse": 22, "emotionId": "neutral", "emotionTags": ["neutral"], "tags": ["fruit", "spirit"], "tier": "premium", "weight": 8 },
  { "book": "Galatians", "chapter": 5, "verse": 23, "emotionId": "neutral", "emotionTags": ["neutral"], "tags": ["self-control", "spirit"], "tier": "premium", "weight": 8 },
  { "book": "Deuteronomy", "chapter": 29, "verse": 29, "emotionId": "neutral", "emotionTags": ["neutral"], "tags": ["hidden", "revealed"], "tier": "premium", "weight": 8 },
  { "book": "Psalm", "chapter": 90, "verse": 12, "emotionId": "neutral", "emotionTags": ["neutral"], "tags": ["days", "wisdom"], "tier": "premium", "weight": 8 },
  { "book": "Matthew", "chapter": 5, "verse": 14, "emotionId": "neutral", "emotionTags": ["neutral"], "tags": ["light", "world"], "tier": "premium", "weight": 8 },
  { "book": "Matthew", "chapter": 5, "verse": 16, "emotionId": "neutral", "emotionTags": ["neutral"], "tags": ["shine", "good"], "tier": "premium", "weight": 8 },
  { "book": "Isaiah", "chapter": 43, "verse": 19, "emotionId": "neutral", "emotionTags": ["neutral"], "tags": ["new", "way"], "tier": "premium", "weight": 9 },
  { "book": "Psalm", "chapter": 25, "verse": 4, "emotionId": "neutral", "emotionTags": ["neutral"], "tags": ["ways", "teach"], "tier": "premium", "weight": 8 },
  { "book": "Psalm", "chapter": 25, "verse": 5, "emotionId": "neutral", "emotionTags": ["neutral"], "tags": ["truth", "lead"], "tier": "premium", "weight": 8 },
  { "book": "John", "chapter": 15, "verse": 4, "emotionId": "neutral", "emotionTags": ["neutral"], "tags": ["abide", "fruit"], "tier": "premium", "weight": 8 },
  { "book": "John", "chapter": 15, "verse": 5, "emotionId": "neutral", "emotionTags": ["neutral"], "tags": ["vine", "fruit"], "tier": "premium", "weight": 8 },
  { "book": "Psalm", "chapter": 84, "verse": 10, "emotionId": "neutral", "emotionTags": ["neutral"], "tags": ["courts", "dwelling"], "tier": "premium", "weight": 8 },
  { "book": "Numbers", "chapter": 6, "verse": 24, "emotionId": "neutral", "emotionTags": ["neutral"], "tags": ["blessing", "keep"], "tier": "premium", "weight": 8 },
  { "book": "Numbers", "chapter": 6, "verse": 25, "emotionId": "neutral", "emotionTags": ["neutral"], "tags": ["face", "gracious"], "tier": "premium", "weight": 8 },
  { "book": "Numbers", "chapter": 6, "verse": 26, "emotionId": "neutral", "emotionTags": ["neutral"], "tags": ["peace", "countenance"], "tier": "premium", "weight": 8 },
  { "book": "1 Timothy", "chapter": 6, "verse": 6, "emotionId": "neutral", "emotionTags": ["neutral"], "tags": ["contentment", "gain"], "tier": "premium", "weight": 8 },

  { "book": "Psalm", "chapter": 118, "verse": 24, "emotionId": "good", "emotionTags": ["good"], "tags": ["rejoice", "day"], "tier": "free", "weight": 10 },
  { "book": "Psalm", "chapter": 100, "verse": 4, "emotionId": "good", "emotionTags": ["good"], "tags": ["thanksgiving", "praise"], "tier": "free", "weight": 10 },
  { "book": "Psalm", "chapter": 100, "verse": 5, "emotionId": "good", "emotionTags": ["good"], "tags": ["good", "love"], "tier": "free", "weight": 10 },
  { "book": "Philippians", "chapter": 4, "verse": 4, "emotionId": "good", "emotionTags": ["good"], "tags": ["rejoice", "always"], "tier": "free", "weight": 10 },
  { "book": "1 Thessalonians", "chapter": 5, "verse": 18, "emotionId": "good", "emotionTags": ["good"], "tags": ["thanksgiving", "always"], "tier": "free", "weight": 9 },
  { "book": "James", "chapter": 1, "verse": 17, "emotionId": "good", "emotionTags": ["good"], "tags": ["gift", "perfect"], "tier": "free", "weight": 9 },
  { "book": "Psalm", "chapter": 28, "verse": 7, "emotionId": "good", "emotionTags": ["good"], "tags": ["rejoice", "trust"], "tier": "free", "weight": 9 },
  { "book": "Psalm", "chapter": 16, "verse": 11, "emotionId": "good", "emotionTags": ["good"], "tags": ["joy", "presence"], "tier": "free", "weight": 9 },
  { "book": "Nehemiah", "chapter": 8, "verse": 10, "emotionId": "good", "emotionTags": ["good"], "tags": ["joy", "strength"], "tier": "free", "weight": 9 },
  { "book": "Romans", "chapter": 8, "verse": 28, "emotionId": "good", "emotionTags": ["good"], "tags": ["good", "purpose"], "tier": "free", "weight": 9 },
  { "book": "John", "chapter": 16, "verse": 33, "emotionId": "good", "emotionTags": ["good"], "tags": ["peace", "overcome"], "tier": "free", "weight": 9 },
  { "book": "Psalm", "chapter": 34, "verse": 8, "emotionId": "good", "emotionTags": ["good"], "tags": ["taste", "good"], "tier": "free", "weight": 9 },
  { "book": "Psalm", "chapter": 145, "verse": 7, "emotionId": "good", "emotionTags": ["good"], "tags": ["goodness", "sing"], "tier": "free", "weight": 8 },
  { "book": "Psalm", "chapter": 107, "verse": 1, "emotionId": "good", "emotionTags": ["good"], "tags": ["good", "love"], "tier": "free", "weight": 9 },
  { "book": "Psalm", "chapter": 36, "verse": 7, "emotionId": "good", "emotionTags": ["good"], "tags": ["love", "wings"], "tier": "free", "weight": 8 },
  { "book": "Zephaniah", "chapter": 3, "verse": 17, "emotionId": "good", "emotionTags": ["good"], "tags": ["singing", "delight"], "tier": "free", "weight": 9 },
  { "book": "Ephesians", "chapter": 3, "verse": 20, "emotionId": "good", "emotionTags": ["good"], "tags": ["abundantly", "ask"], "tier": "free", "weight": 9 },
  { "book": "2 Corinthians", "chapter": 9, "verse": 8, "emotionId": "good", "emotionTags": ["good"], "tags": ["grace", "abundance"], "tier": "free", "weight": 8 },
  { "book": "Isaiah", "chapter": 12, "verse": 2, "emotionId": "good", "emotionTags": ["good"], "tags": ["trust", "salvation"], "tier": "free", "weight": 8 },
  { "book": "Isaiah", "chapter": 12, "verse": 4, "emotionId": "good", "emotionTags": ["good"], "tags": ["name", "declare"], "tier": "free", "weight": 8 },
  { "book": "Psalm", "chapter": 96, "verse": 1, "emotionId": "good", "emotionTags": ["good"], "tags": ["sing", "new"], "tier": "free", "weight": 8 },
  { "book": "Psalm", "chapter": 96, "verse": 2, "emotionId": "good", "emotionTags": ["good"], "tags": ["bless", "salvation"], "tier": "free", "weight": 8 },
  { "book": "Habakkuk", "chapter": 3, "verse": 18, "emotionId": "good", "emotionTags": ["good"], "tags": ["rejoice", "joy"], "tier": "free", "weight": 8 },
  { "book": "Psalm", "chapter": 150, "verse": 6, "emotionId": "good", "emotionTags": ["good"], "tags": ["praise", "breath"], "tier": "free", "weight": 8 },
  { "book": "1 Peter", "chapter": 1, "verse": 8, "emotionId": "good", "emotionTags": ["good"], "tags": ["joy", "believing"], "tier": "free", "weight": 9 },
  { "book": "Psalm", "chapter": 19, "verse": 1, "emotionId": "good", "emotionTags": ["good"], "tags": ["glory", "creation"], "tier": "premium", "weight": 9 },
  { "book": "Psalm", "chapter": 19, "verse": 8, "emotionId": "good", "emotionTags": ["good"], "tags": ["heart", "pure"], "tier": "premium", "weight": 8 },
  { "book": "Psalm", "chapter": 21, "verse": 6, "emotionId": "good", "emotionTags": ["good"], "tags": ["joy", "presence"], "tier": "premium", "weight": 8 },
  { "book": "Romans", "chapter": 5, "verse": 11, "emotionId": "good", "emotionTags": ["good"], "tags": ["rejoice", "reconciled"], "tier": "premium", "weight": 8 },
  { "book": "Philippians", "chapter": 4, "verse": 8, "emotionId": "good", "emotionTags": ["good"], "tags": ["think", "good"], "tier": "premium", "weight": 9 },
  { "book": "Colossians", "chapter": 3, "verse": 17, "emotionId": "good", "emotionTags": ["good"], "tags": ["thanksgiving", "name"], "tier": "premium", "weight": 8 },
  { "book": "Psalm", "chapter": 9, "verse": 1, "emotionId": "good", "emotionTags": ["good"], "tags": ["praise", "wonderful"], "tier": "premium", "weight": 8 },
  { "book": "John", "chapter": 15, "verse": 11, "emotionId": "good", "emotionTags": ["good"], "tags": ["joy", "full"], "tier": "premium", "weight": 9 },
  { "book": "1 Chronicles", "chapter": 16, "verse": 34, "emotionId": "good", "emotionTags": ["good"], "tags": ["good", "endures"], "tier": "premium", "weight": 8 },
  { "book": "Psalm", "chapter": 65, "verse": 11, "emotionId": "good", "emotionTags": ["good"], "tags": ["goodness", "crown"], "tier": "premium", "weight": 8 },
  { "book": "Psalm", "chapter": 68, "verse": 19, "emotionId": "good", "emotionTags": ["good"], "tags": ["blessed", "bears"], "tier": "premium", "weight": 8 },
  { "book": "Psalm", "chapter": 84, "verse": 11, "emotionId": "good", "emotionTags": ["good"], "tags": ["sun", "good"], "tier": "premium", "weight": 8 },
  { "book": "Isaiah", "chapter": 64, "verse": 4, "emotionId": "good", "emotionTags": ["good"], "tags": ["seen", "waits"], "tier": "premium", "weight": 8 },
  { "book": "Deuteronomy", "chapter": 7, "verse": 9, "emotionId": "good", "emotionTags": ["good"], "tags": ["faithful", "love"], "tier": "premium", "weight": 8 },
  { "book": "Lamentations", "chapter": 3, "verse": 25, "emotionId": "good", "emotionTags": ["good"], "tags": ["good", "waiting"], "tier": "premium", "weight": 8 },
  { "book": "Acts", "chapter": 2, "verse": 28, "emotionId": "good", "emotionTags": ["good"], "tags": ["joy", "presence"], "tier": "premium", "weight": 8 },
  { "book": "Genesis", "chapter": 1, "verse": 31, "emotionId": "good", "emotionTags": ["good"], "tags": ["very good", "creation"], "tier": "premium", "weight": 8 },
  { "book": "Psalm", "chapter": 31, "verse": 19, "emotionId": "good", "emotionTags": ["good"], "tags": ["goodness", "stored"], "tier": "premium", "weight": 8 },
  { "book": "Romans", "chapter": 11, "verse": 36, "emotionId": "good", "emotionTags": ["good"], "tags": ["glory", "all"], "tier": "premium", "weight": 8 },
  { "book": "Psalm", "chapter": 23, "verse": 6, "emotionId": "good", "emotionTags": ["good"], "tags": ["goodness", "mercy"], "tier": "premium", "weight": 9 },
  { "book": "Psalm", "chapter": 145, "verse": 9, "emotionId": "good", "emotionTags": ["good"], "tags": ["good", "mercies"], "tier": "premium", "weight": 8 },
  { "book": "Psalm", "chapter": 103, "verse": 1, "emotionId": "good", "emotionTags": ["good"], "tags": ["praise", "soul"], "tier": "premium", "weight": 9 },
  { "book": "Psalm", "chapter": 103, "verse": 2, "emotionId": "good", "emotionTags": ["good"], "tags": ["forget not", "benefits"], "tier": "premium", "weight": 9 },
  { "book": "Psalm", "chapter": 103, "verse": 3, "emotionId": "good", "emotionTags": ["good"], "tags": ["forgiveness", "healing"], "tier": "premium", "weight": 8 },
  { "book": "Psalm", "chapter": 103, "verse": 4, "emotionId": "good", "emotionTags": ["good"], "tags": ["love", "crown"], "tier": "premium", "weight": 8 }
]
